<?xml version="1.0" encoding="utf-8"?>
<Allchamps xmlns:xsi="http://www.w3.org/2001/XMLSchema-instance" xmlns:xsd="http://www.w3.org/2001/XMLSchema">
  <Champs>
    <Champion>Ezreal</Champion>
    <Filename>HuyNKSeries</Filename>
    <Creator>HuyNK</Creator>
    <Status>Working</Status>
    <Github>https://github.com/huynkprovn/HuyNK-Ass</Github>
    <Install>ls://project/huynkprovn/Huynk-Ass/HuyNKSeries/</Install>
  </Champs>
  <Champs>
    <Champion>Kalista</Champion>
    <Filename>HuyNKSeries</Filename>
    <Creator>HuyNK</Creator>
    <Status>Working</Status>
    <Github>https://github.com/huynkprovn/HuyNK-Ass</Github>
    <Install>ls://project/huynkprovn/Huynk-Ass/HuyNKSeries/</Install>
  </Champs>
  <Champs>
    <Champion>Teemo</Champion>
    <Filename>HuyNKSeries</Filename>
    <Creator>HuyNK</Creator>
    <Status>Working</Status>
    <Github>https://github.com/huynkprovn/HuyNK-Ass</Github>
    <Install>ls://project/huynkprovn/Huynk-Ass/HuyNKSeries/</Install>
  </Champs>

</Allchamps>